README.md
setup.cfg
setup.py
dotcastles/dotcastles.py
dotcastles.egg-info/PKG-INFO
dotcastles.egg-info/SOURCES.txt
dotcastles.egg-info/dependency_links.txt
dotcastles.egg-info/entry_points.txt
dotcastles.egg-info/requires.txt
dotcastles.egg-info/top_level.txt