Metadata-Version: 1.1
Name: dotcastles
Version: 0.1.6
Summary: Shares your dotfiles through git
Home-page: https://github.com/pescuma/dotcastles
Author: Ricardo Pescuma Domenecci
Author-email: ricardo@pescuma.org
License: GPL
Download-URL: https://github.com/pescuma/dotcastles/tarball/v0.1.6
Keywords: dotfiles
Platform: UNKNOWN
